{
    "events": [{
        "event": "a0edd5ba4b2",
        "status": "ACTIVE",
        "program": "ad7fe0ff2af",
        "programStage": "ad5d2115e14",
        "orgUnit": "aeddcd62beb",
        "orgUnitName": "Not Specified",
        "eventDate": "2015-06-14T00:00:00",
        "dataValues": [{
            "value": "2015-06-14",
            "dataElement": "ab37357f9a2",
            "providedElsewhere": false,
            "storedBy": "service.account"
        }, {
            "value": "a72123c7388",
            "dataElement": "a30b16e4d0f",
            "providedElsewhere": false,
            "storedBy": "service.account"
        }, {
            "value": "123",
            "dataElement": "a23d603a070",
            "providedElsewhere": false,
            "storedBy": "service.account"
        }, {
            "value": "PI",
            "dataElement": "a5c51a340f0",
            "providedElsewhere": false,
            "storedBy": "service.account"
        }, {
            "value": "12",
            "dataElement": "a86a265afb7",
            "providedElsewhere": false,
            "storedBy": "service.account"
        }, {
            "value": "add59a95149",
            "dataElement": "a56f065f738",
            "providedElsewhere": false,
            "storedBy": "service.account"
        }, {
            "value": "a37e2f77624",
            "dataElement": "a94e93a5c64",
            "providedElsewhere": false,
            "storedBy": "service.account"
        }, {
            "value": "aa1ab2b5d46",
            "dataElement": "ac27dbbb4b3",
            "providedElsewhere": false,
            "storedBy": "service.account"
        }, {
            "value": "a3159c01e56",
            "dataElement": "ad03b1b1aa8",
            "providedElsewhere": false,
            "storedBy": "service.account"
        }, {
            "value": "ad380e9fd96",
            "dataElement": "aa3029f4abe",
            "providedElsewhere": false,
            "storedBy": "service.account"
        }, {
            "value": "a6c90fc7021",
            "dataElement": "a4e2acb9ad7",
            "providedElsewhere": false,
            "storedBy": "service.account"
        }, {
            "value": "a6c90fc7021",
            "dataElement": "a396614bc09",
            "providedElsewhere": false,
            "storedBy": "service.account"
        }, {
            "value": "aeb00fe6f15",
            "dataElement": "a4c0b238647",
            "providedElsewhere": false,
            "storedBy": "service.account"
        }, {
            "value": "a973d3ab0c5",
            "dataElement": "aebe5661a39",
            "providedElsewhere": false,
            "storedBy": "service.account"
        }, {
            "value": "ab805071962",
            "dataElement": "aba9ff4bccd",
            "providedElsewhere": false,
            "storedBy": "service.account"
        }, {
            "value": "2014-12-31",
            "dataElement": "abf88fe3508",
            "providedElsewhere": false,
            "storedBy": "service.account"
        }, {
            "value": "a6341f24a01",
            "dataElement": "a922aac45da",
            "providedElsewhere": false,
            "storedBy": "service.account"
        }, {
            "value": "a72123c7388",
            "dataElement": "a29a6612d2d",
            "providedElsewhere": false,
            "storedBy": "service.account"
        }]
    }]
}
